papanda/__init__.py
papanda/cochran_test.py
papanda/gesd.py
papanda/greenwood_criterion.py
papanda/modified_boxplot.py
papanda/trimmed_mean.py
papanda/datasets/cochran.xlsx
papanda/datasets/coef.xlsx
papanda/datasets/greenwood_1.xlsx
papanda-0.0.1a4.dist-info/LICENSE.txt
papanda-0.0.1a4.dist-info/METADATA
papanda-0.0.1a4.dist-info/WHEEL
papanda-0.0.1a4.dist-info/top_level.txt
papanda-0.0.1a4.dist-info/RECORD
